{
    "result": {
        "app": {
            "version": 13961,
            "timestamp": 1697231754,
            "time": "Fri Oct 13 14:15:54 2023"
        },
        "services": {
            "SessionsLogon": "normal",
            "SteamCommunity": "normal",
            "IEconItems": "offline",
            "Leaderboards": "idle"
        },
        "datacenters": {
            "Peru": {
                "capacity": "full",
                "load": "low"
            },
            "EU Germany": {
                "capacity": "full",
                "load": "low"
            },
            "EU Austria": {
                "capacity": "full",
                "load": "high"
            },
            "EU Poland": {
                "capacity": "full",
                "load": "high"
            },
            "India East": {
                "capacity": "full",
                "load": "low"
            },
            "Hong Kong": {
                "capacity": "full",
                "load": "low"
            },
            "EU Spain": {
                "capacity": "full",
                "load": "medium"
            },
            "Chile": {
                "capacity": "full",
                "load": "low"
            },
            "US California": {
                "capacity": "full",
                "load": "low"
            },
            "US Atlanta": {
                "capacity": "full",
                "load": "low"
            },
            "India": {
                "capacity": "full",
                "load": "medium"
            },
            "EU Sweden": {
                "capacity": "full",
                "load": "medium"
            },
            "Emirates": {
                "capacity": "full",
                "load": "low"
            },
            "US Seattle": {
                "capacity": "full",
                "load": "low"
            },
            "South Africa": {
                "capacity": "full",
                "load": "low"
            },
            "Brazil": {
                "capacity": "full",
                "load": "medium"
            },
            "US Virginia": {
                "capacity": "full",
                "load": "low"
            },
            "US Chicago": {
                "capacity": "full",
                "load": "low"
            },
            "Japan": {
                "capacity": "full",
                "load": "idle"
            },
            "EU Holland": {
                "capacity": "full",
                "load": "high"
            },
            "US NewYork": {
                "capacity": "full",
                "load": "full"
            },
            "EU Finland": {
                "capacity": "full",
                "load": "full"
            },
            "Argentina": {
                "capacity": "full",
                "load": "low"
            },
            "South Korea": {
                "capacity": "full",
                "load": "idle"
            },
            "Singapore": {
                "capacity": "full",
                "load": "low"
            },
            "Australia": {
                "capacity": "full",
                "load": "idle"
            },
            "China Chengdu": {
                "capacity": "full",
                "load": "low"
            },
            "China Shanghai": {
                "capacity": "full",
                "load": "idle"
            },
            "China Tianjin": {
                "capacity": "full",
                "load": "idle"
            },
            "China Guangzhou": {
                "capacity": "full",
                "load": "idle"
            }
        },
        "matchmaking": {
            "scheduler": "normal",
            "online_servers": 196389,
            "online_players": 710010,
            "searching_players": 12900,
            "search_seconds_avg": 50
        },
        "perfectworld": {
            "logon": {
                "availability": "online",
                "latency": "normal"
            },
            "purchase": {
                "availability": "online",
                "latency": "normal"
            }
        }
    }
}